{"barque":{"M":[],"S":["Barque","Bark"],"A":[]},"barques":{"M":[],"S":["Barque","Bark"],"A":[]},"barrack":{"M":[["Verb","lodge in barracks",["Lodge","Accommodate"],[]]],"S":["Barrack","Urge on","Exhort","Gibe","Flout"],"A":[]},"barracked":{"M":[],"S":["Barrack","Urge on","Exhort","Gibe","Flout"],"A":[]},"barracking":{"M":[],"S":["Barrack","Urge on","Exhort","Gibe","Flout"],"A":[]},"barracks":{"M":[],"S":["Barrack","Urge on","Exhort","Gibe","Flout"],"A":[]},"barracouta":{"M":[["Noun","a large marine food fish common on the coasts of Australia, New Zealand, and southern Africa",["Food fish"],[]]],"S":["Snoek","Barracouta"],"A":[]},"barracoutas":{"M":[],"S":["Snoek","Barracouta"],"A":[]},"barracuda":{"M":[["Noun","any voracious marine fish of the genus Sphyraena having an elongated cylindrical body and large mouth with projecting lower jaw and long strong teeth",["Spiny-finned fish","Acanthopterygian"],[]]],"S":["Barracuda"],"A":[]},"barracudas":{"M":[],"S":["Barracuda"],"A":[]},"barrage":{"M":[["Noun","the rapid and continuous delivery of linguistic communication (spoken or written)",["Language","Linguistic communication"],["a barrage of questions","a bombardment of mail complaining about his mistake"]],["Noun","the heavy fire of artillery to saturate an area rather than hit a specific target",["Fire","Firing"],["they laid down a barrage in front of the advancing troops","the shelling went on for hours without pausing"]]],"S":["Barrage fire","Bombard","Barrage","Battery","Bombardment"],"A":[]},"barraged":{"M":[],"S":["Barrage","Bombard"],"A":[]},"barrages":{"M":[],"S":["Barrage fire","Bombard","Barrage","Battery","Bombardment"],"A":[]},"barraging":{"M":[],"S":["Barrage","Bombard"],"A":[]},"barramundi":{"M":[["Noun","a species of large perch noted for its sporting and eating qualities; lives in marine, estuary, and freshwater habitats",["Fish species"],[]]],"S":["Asian seabass","Giant seaperch","Giant perch","Lates calcarifer","Barramundi"],"A":[]},"barramundies":{"M":[],"S":["Asian seabass","Giant seaperch","Giant perch","Lates calcarifer","Barramundi"],"A":[]},"barramundis":{"M":[],"S":["Asian seabass","Giant seaperch","Giant perch","Lates calcarifer","Barramundi"],"A":[]},"barranquilla":{"M":[["Noun","a port city of northern Colombia near the Caribbean on the Magdalena River",[],[]]],"S":["Barranquilla"],"A":[]},"barrater":{"M":[],"S":["Barrater","Barrator"],"A":[]},"barraters":{"M":[],"S":["Barrater","Barrator"],"A":[]},"barrator":{"M":[["Noun","someone guilty of barratry",["Wrongdoer","Offender"],[]]],"S":["Barrater","Barrator"],"A":[]},"barrators":{"M":[],"S":["Barrater","Barrator"],"A":[]},"barratries":{"M":[],"S":["Barratry","Simony"],"A":[]},"barratry":{"M":[["Noun","the crime of a judge whose judgment is influenced by bribery",["Bribery","Graft"],[]],["Noun","(maritime law) a fraudulent breach of duty by the master of a ship that injures the owner of the ship or its cargo; includes every breach of trust such as stealing or sinking or deserting the ship or embezzling the cargo",["Fraud"],[]],["Noun","the offense of vexatiously persisting in inciting lawsuits and quarrels",["Crime","Offense","Criminal offense","Criminal offence","Offence","Law-breaking"],[]]],"S":["Barratry","Simony"],"A":[]},"barred":{"M":[["Adjective","marked with stripes or bands",[],[]]],"S":["Exclude","Block off","Relegate","Barricaded","Barricade"],"A":["unbar"]},"barrel":{"M":[["Verb","put in barrels",["Put","Set","Place","Pose","Position","Lay"],[]],["Noun","a cylindrical container that holds liquids",["Vessel"],[]],["Noun","a bulging cylindrical shape; hollow with flat ends",["Cylinder"],[]],["Noun","the quantity that a barrel (of any size) will hold",["Containerful"],[]],["Noun","any of various units of capacity",["British capacity unit","Imperial capacity unit","United states liquid unit"],["a barrel of beer is 31 gallons and a barrel of oil is 42 gallons"]]],"S":["Barrelful","Barrel","Bbl","Gun barrel","Cask"],"A":[]},"barrel-shaped":{"M":[["Adjective","having the general shape of a barrel",[],[]]],"S":["Barrel-shaped"],"A":[]},"barreled":{"M":[["Adjective","put in or stored in a barrel",[],["barreled beer"]],["Adjective","(of an arrow) tapered toward both ends",[],[]]],"S":["Barrel","Barreled","Barrelled"],"A":["unbarreled"]},"barrelfish":{"M":[["Noun","blackish fish of New England waters",["Butterfish","Stromateid fish","Stromateid"],[]]],"S":["Barrelfish","Hyperglyphe perciformis","Black rudderfish"],"A":[]},"barrelfishes":{"M":[],"S":["Barrelfish","Hyperglyphe perciformis","Black rudderfish"],"A":[]},"barrelful":{"M":[],"S":["Barrelful","Barrel"],"A":[]},"barrelfuls":{"M":[],"S":["Barrelful","Barrel"],"A":[]},"barrelhouse":{"M":[["Noun","a cheap drinking and dancing establishment",["Barroom","Bar","Saloon","Ginmill","Taproom"],[]]],"S":["Barrelhouse","Honky-tonk"],"A":[]},"barrelhouses":{"M":[],"S":["Barrelhouse","Honky-tonk"],"A":[]},"barreling":{"M":[],"S":["Barrel"],"A":[]},"barrelled":{"M":[],"S":["Barrel","Barreled","Barrelled"],"A":["unbarreled"]},"barrelling":{"M":[],"S":["Barrel"],"A":[]},"barrels":{"M":[["Noun","the amount that many barrels might hold",["Large indefinite quantity","Large indefinite amount"],[]]],"S":["Barrel","Barrelful","Barrels","Bbl","Gun barrel"],"A":[]},"barren":{"M":[["Noun","an uninhabited wilderness that is worthless for cultivation",["Wilderness","Wild"],["the barrens of central Africa","the trackless wastes of the desert"]],["Adjective","not bearing offspring",[],["a barren woman","learned early in his marriage that he was sterile"]],["Adjective","completely wanting or lacking",[],["writing barren of insight","young recruits destitute of experience","innocent of literary merit","the sentence was devoid of meaning"]]],"S":["Desolate","Destitute","Free","Devoid","Bare"],"A":[]},"barrener":{"M":[],"S":["Desolate","Destitute","Free","Devoid","Bare"],"A":[]},"barrenest":{"M":[],"S":["Desolate","Destitute","Free","Devoid","Bare"],"A":[]},"barrenness":{"M":[["Noun","the state (usually of a woman) of having no children or being unable to have children",["Sterility","Infertility"],[]]],"S":["Fruitlessness","Barrenness","Aridity"],"A":["fruitfulness"]},"barrennesses":{"M":[],"S":["Fruitlessness","Barrenness","Aridity"],"A":["fruitfulness"]},"barrens":{"M":[],"S":["Barren","Wasteland","Waste"],"A":[]},"barrenwort":{"M":[["Noun","slow-growing creeping plant with semi-evergreen leaves on erect wiry stems; used as ground cover",["Herb","Herbaceous plant"],[]]],"S":["Epimedium grandiflorum","Barrenwort","Bishop's hat"],"A":[]},"barrette":{"M":[["Noun","a pin for holding women's hair in place",["Pin"],[]]],"S":["Barrette"],"A":[]},"barretter":{"M":[],"S":["Barretter","Ballast","Ballast resistor"],"A":[]},"barrettes":{"M":[],"S":["Barrette"],"A":[]},"barricade":{"M":[["Verb","prevent access to by barricading",["Obstruct","Obturate","Impede","Occlude","Jam","Block","Close up"],["The street where the President lives is always barricaded"]],["Verb","render unsuitable for passage",["Obstruct","Obturate","Impede","Occlude","Jam","Block","Close up"],["block the way","barricade the streets","stop the busy road"]],["Verb","block off with barricades",["Obstruct","Obturate","Impede","Occlude","Jam","Block","Close up"],[]]],"S":["Block off","Roadblock","Barricade","Block up","Stop"],"A":[]},"barricaded":{"M":[["Adjective","preventing entry or exit or a course of action",[],["a barricaded street","barred doors","the blockaded harbor"]]],"S":["Block off","Barricaded","Barricade","Block up","Blockaded"],"A":[]},"barricades":{"M":[],"S":["Block off","Roadblock","Barricade","Block up","Stop"],"A":[]},"barricading":{"M":[],"S":["Block off","Barricade","Block up","Stop","Block"],"A":[]},"barricado":{"M":[],"S":["Barricade","Barricado"],"A":[]},"barricadoed":{"M":[],"S":["Barricade","Barricado"],"A":[]},"barricadoes":{"M":[],"S":["Barricade","Barricado"],"A":[]},"barricadoing":{"M":[],"S":["Barricade","Barricado"],"A":[]},"barricados":{"M":[],"S":["Barricade","Barricado"],"A":[]},"barrie":{"M":[["Noun","Scottish dramatist and novelist; created Peter Pan (1860-1937)",[],[]]],"S":["James matthew barrie","Barrie","J. m. barrie","Sir james matthew barrie","James barrie"],"A":[]},"barrier":{"M":[["Noun","a structure or object that impedes free movement",["Obstruction","Obstructor","Obstructer","Impediment","Impedimenta"],[]],["Noun","any condition that makes it difficult to make progress or to achieve an objective",["Obstacle","Obstruction"],["intolerance is a barrier to understanding"]],["Noun","anything serving to maintain separation by obstructing vision or access",["Mechanism"],[]]],"S":["Roadblock","Barrier"],"A":[]},"barriers":{"M":[],"S":["Roadblock","Barrier"],"A":[]},"barring":{"M":[["Noun","the act of excluding someone by a negative vote or veto",["Ejection","Exclusion","Expulsion","Riddance"],[]]],"S":["Exclude","Block off","Relegate","Blackball","Barring"],"A":["unbar"]},"barrio":{"M":[["Noun","a Spanish-speaking quarter in a town or city (especially in the United States)",["Quarter"],[]],["Noun","an urban area in a Spanish-speaking country",["Urban area","Populated area"],[]]],"S":["Barrio"],"A":[]},"barrios":{"M":[],"S":["Barrio"],"A":[]},"barrister":{"M":[["Noun","a British or Canadian lawyer who speaks in the higher courts of law on behalf of either the defense or prosecution",["Lawyer","Attorney"],[]]],"S":["Barrister"],"A":[]},"barristers":{"M":[],"S":["Barrister"],"A":[]},"barroom":{"M":[["Noun","a room or establishment where alcoholic drinks are served over a counter",["Room"],["he drowned his sorrows in whiskey at the bar"]]],"S":["Saloon","Barroom","Ginmill","Taproom","Bar"],"A":[]},"barrooms":{"M":[],"S":["Saloon","Barroom","Ginmill","Taproom","Bar"],"A":[]},"barrow":{"M":[["Noun","the quantity that a barrow will hold",["Containerful"],[]],["Noun","a cart for carrying small loads; has handles and one or more wheels",["Handcart","Pushcart","Cart","Go-cart"],[]]],"S":["Wheelbarrow","Barrowful","Lawn cart","Garden cart","Barrow"],"A":[]},"barrow-boy":{"M":[],"S":["Costermonger","Barrow-boy","Barrow-man"],"A":[]},"barrow-man":{"M":[],"S":["Costermonger","Barrow-boy","Barrow-man"],"A":[]},"barrow-men":{"M":[],"S":["Costermonger","Barrow-boy","Barrow-man"],"A":[]},"barrowful":{"M":[],"S":["Barrow","Barrowful"],"A":[]},"barrows":{"M":[],"S":["Wheelbarrow","Barrowful","Lawn cart","Garden cart","Barrow"],"A":[]},"barrymore":{"M":[["Noun","United States actor; son of Maurice Barrymore and Georgiana Barrymore (1882-1942)",[],[]],["Noun","United States actress; daughter of Maurice Barrymore and Georgiana Barrymore (1879-1959)",[],[]],["Noun","United States actor; son of Maurice Barrymore and Georgiana Barrymore (1878-1954)",[],[]],["Noun","United States actress; daughter of John Drew and wife of Maurice Barrymore; mother of Ethel Barrymore and John Barrymore and Lionel Barrymore (1854-1893)",[],[]],["Noun","United States actor; husband of Georgiana Emma Barrymore and father of Ethel Barrymore and John Barrymore and Lionel Barrymore (1847-1905)",[],[]]],"S":["John barrymore","Herbert blythe","Georgiana barrymore","Georgiana emma barrymore","Lionel barrymore"],"A":[]},"bars":{"M":[],"S":["Saloon","Exclude","Prevention","Relegate","Block up"],"A":["unbar"]},"barstow":{"M":[["Noun","a town in southeastern California",[],[]]],"S":["Barstow"],"A":[]},"bart":{"M":[],"S":["Bart","Baronet"],"A":[]},"bartender":{"M":[["Noun","an employee who mixes and serves alcoholic drinks at a bar",["Employee"],[]]],"S":["Barkeeper","Bartender","Mixologist","Barman","Barkeep"],"A":[]},"bartenders":{"M":[],"S":["Barkeeper","Bartender","Mixologist","Barman","Barkeep"],"A":[]},"barter":{"M":[["Verb","exchange goods without involving money",["Exchange","Change","Interchange"],[]]],"S":["Trade","Swop","Swap","Barter"],"A":[]},"bartered":{"M":[],"S":["Barter"],"A":[]},"barterer":{"M":[["Noun","a trader who exchanges goods and not money",["Trader","Bargainer","Dealer","Monger"],[]]],"S":["Barterer"],"A":[]},"barterers":{"M":[],"S":["Barterer"],"A":[]},"bartering":{"M":[],"S":["Barter"],"A":[]},"barters":{"M":[],"S":["Trade","Swop","Swap","Barter"],"A":[]},"barth":{"M":[["Noun","Swiss Protestant theologian (1886-1968)",[],[]],["Noun","United States novelist (born in 1930)",[],[]]],"S":["John simmons barth","John barth","Barth","Karl barth"],"A":[]},"bartholdi":{"M":[["Noun","French sculptor best known for creating the Statue of Liberty now in New York harbor",[],[]]],"S":["Frederic auguste bartholdi","Bartholdi"],"A":[]},"bartlesville":{"M":[["Noun","a town in northeastern Oklahoma",[],[]]],"S":["Bartlesville"],"A":[]},"bartlett":{"M":[["Noun","United States explorer who accompanied Peary's expedition to the North Pole and who led many other Arctic trips (1875-1946)",[],[]],["Noun","United States publisher and editor who compiled a book of familiar quotations (1820-1905)",[],[]],["Noun","juicy yellow pear",["Pear"],[]]],"S":["John bartlett","Bartlett","Robert bartlett","Captain bob","Robert abram bartlett"],"A":[]},"bartletts":{"M":[],"S":["John bartlett","Bartlett","Robert bartlett","Captain bob","Robert abram bartlett"],"A":[]},"bartok":{"M":[["Noun","Hungarian composer and pianist who collected Hungarian folk music; in 1940 he moved to the United States (1881-1945)",[],[]]],"S":["Bartok","Bela bartok"],"A":[]},"bartonia":{"M":[["Noun","annual grown especially for its fragrant golden nocturnal flowers",["Flower"],[]]],"S":["Bartonia","Mentzelia lindleyi"],"A":[]},"bartramia":{"M":[["Noun","a genus of Scolopacidae",["Bird genus"],[]]],"S":["Genus bartramia","Bartramia"],"A":[]},"baruch":{"M":[["Noun","economic advisor to United States Presidents (1870-1965)",[],[]],["Noun","a disciple of and secretary for the prophet Jeremiah",[],[]],["Noun","an Apocryphal book ascribed to Baruch",[],[]]],"S":["Bernard baruch","Book of baruch","Bernard mannes baruch","Baruch"],"A":[]},"barycenter":{"M":[["Noun","(astronomy) the common center of mass around which two or more bodies revolve",["Center of mass","Centre of mass"],[]]],"S":["Barycenter"],"A":[]},"barye":{"M":[["Noun","the absolute unit of pressure equal to one dyne per square centimeter",["Pressure unit"],[]]],"S":["Bar absolute","Microbar","Barye"],"A":[]},"baryes":{"M":[],"S":["Bar absolute","Microbar","Barye"],"A":[]},"baryon":{"M":[["Noun","any of the elementary particles having a mass equal to or greater than that of a proton and that participate in strong interactions; a hadron with a baryon number of +1",["Fermion","Hadron"],[]]],"S":["Heavy particle","Baryon"],"A":[]},"baryons":{"M":[],"S":["Heavy particle","Baryon"],"A":[]},"baryta":{"M":[["Noun","any of several compounds of barium",["Barium","Ba","Atomic number 56"],[]]],"S":["Baryta"],"A":[]}}