{"rainwater":{"M":[],"S":["Rainwater","Rain"],"A":[]},"rainwaters":{"M":[],"S":["Rainwater","Rain"],"A":[]},"rainy":{"M":[],"S":["Showery","Rainy"],"A":[]},"raisable":{"M":[["Adjective","capable of being raised",[],["the roadster had a raisable sunroof"]]],"S":["Raiseable","Raisable"],"A":[]},"raise":{"M":[["Verb","raise the level or amount of something",["Increase"],["raise my salary","raise the price of bread"]],["Verb","cause to be heard or known; express or utter",["Express","Verbalize","Verbalise","Utter","Give tongue to"],["raise a shout","raise a protest","raise a sad cry"]],["Verb","raise from a lower to a higher position",["Move","Displace"],["Raise your hands","Lift a load"]],["Verb","collect funds for a specific purpose",["Collect","Take in"],["The President raised several million dollars for his college"]],["Verb","summon into action or bring into existence, often as if by magic",["Make","Create"],["raise the specter of unemployment","he conjured wild birds in the air","call down the spirits from the mountain"]],["Verb","construct, build, or erect",["Construct","Build","Make"],["Raise a barn"]],["Verb","create a disturbance, especially by making a great noise",["Make","Create"],["raise hell","raise the roof","raise Cain"]],["Verb","cause to puff up with a leaven",["Raise","Lift","Elevate","Get up","Bring up"],["unleavened bread"]],["Verb","bid (one's partner's suit) at a higher level",["Bid","Call"],[]],["Verb","bet more than the previous player",["Bet","Wager","Play"],[]],["Verb","put forward for consideration or discussion",["Mention","Advert","Bring up","Cite","Name","Refer"],["raise the question of promotions","bring up an unpleasant topic"]],["Verb","pronounce (vowels) by bringing the tongue closer to the roof of the mouth",["Pronounce","Articulate","Enounce","Sound out","Enunciate","Say"],["raise your `o'"]],["Verb","activate or stir up",["Incite","Instigate","Set off","Stir up"],["raise a mutiny"]],["Verb","establish radio communications with",["Reach","Get through","Get hold of","Contact"],["They managed to raise Hanoi last night"]],["Verb","multiply (a number) by itself a specified number of times: 8 is 2 raised to the power 3",["Multiply"],[]],["Verb","bring (a surface or a design) into relief and cause to project",["Bring out","Set off"],["raised edges"]],["Verb","invigorate or heighten",["Better","Improve","Amend","Ameliorate","Meliorate"],["lift my spirits","lift his ego"]]],"S":["Nurture","Conjure","Enkindle","Farm","Kick upstairs"],"A":["descent","lower","demote","level"]},"raiseable":{"M":[],"S":["Raiseable","Raisable"],"A":[]},"raised":{"M":[["Adjective","located or moved above the surround or above the normal position",[],["a raised design","raised eyebrows"]],["Adjective","increased in amount or degree",[],["raised temperature"]]],"S":["Nurture","Conjure","Enkindle","Farm","Kick upstairs"],"A":["level","lower","lowered","demote"]},"raiser":{"M":[["Noun","a bridge partner who increases the partner's bid",["Bridge partner"],[]]],"S":["Grower","Raiser","Agriculturalist","Cultivator","Agriculturist"],"A":[]},"raisers":{"M":[],"S":["Grower","Raiser","Agriculturalist","Cultivator","Agriculturist"],"A":[]},"raises":{"M":[],"S":["Nurture","Conjure","Enkindle","Farm","Kick upstairs"],"A":["descent","lower","demote","level"]},"raisin":{"M":[["Noun","dried grape",["Dried fruit"],[]]],"S":["Raisin"],"A":[]},"raising":{"M":[["Noun","the properties acquired as a consequence of the way you were treated as a child",["Upbringing"],[]],["Adjective","increasing in quantity or value",[],["a cost-raising increase in the basic wage rate"]]],"S":["Nurture","Conjure","Elevation","Enkindle","Farm"],"A":["level","lower","demote"]},"raisings":{"M":[],"S":["Nurture","Conjure","Elevation","Enkindle","Farm"],"A":["level","lower","demote"]},"raisins":{"M":[],"S":["Raisin"],"A":[]},"raj":{"M":[["Noun","British dominion over India (1757-1947)",["Dominion","Rule"],[]]],"S":["Raj"],"A":[]},"raja":{"M":[["Noun","a prince or king in India",["Aristocrat","Blue blood","Patrician"],[]],["Noun","type genus of the family Rajidae",["Fish genus"],[]]],"S":["Genus raja","Rajah","Raja"],"A":[]},"rajab":{"M":[["Noun","the seventh month of the Islamic calendar",["Islamic calendar month"],[]]],"S":["Rajab"],"A":[]},"rajah":{"M":[],"S":["Rajah","Raja"],"A":[]},"rajahs":{"M":[],"S":["Rajah","Raja"],"A":[]},"rajas":{"M":[],"S":["Genus raja","Rajah","Raja"],"A":[]},"rajidae":{"M":[["Noun","bottom-dwelling tropical rays: skates",["Fish family"],[]]],"S":["Family rajidae","Rajidae"],"A":[]},"rajpoot":{"M":[],"S":["Rajpoot","Rajput"],"A":[]},"rajput":{"M":[["Noun","a member of the dominant Hindu military caste in northern India",["Hindu","Hindoo","Hindustani"],[]]],"S":["Rajpoot","Rajput"],"A":[]},"rake":{"M":[["Verb","move through with or as if with a rake",["Move","Displace"],["She raked her fingers through her hair"]],["Verb","sweep the length of",["Sweep"],["The gunfire raked the coast"]],["Verb","level or smooth with a rake",["Smooth","Smoothen"],["rake gravel"]],["Verb","gather with a rake",["Gather","Garner","Collect","Pull together"],["rake leaves"]]],"S":["Rake","Glance over","Blood","Rakehell","Rip"],"A":[]},"rake-off":{"M":[["Noun","a percentage (of winnings or loot or profit) taken by an operator or gangster",["Cut"],[]]],"S":["Rake-off","Vigorish"],"A":[]},"raked":{"M":[],"S":["Rake","Glance over","Skim","Crease","Run down"],"A":[]},"rakees":{"M":[],"S":["Rake","Glance over","Skim","Crease","Run down"],"A":[]},"rakehell":{"M":[],"S":["Rake","Blood","Rakehell","Rip","Profligate"],"A":[]},"rakehells":{"M":[],"S":["Rake","Blood","Rakehell","Rip","Profligate"],"A":[]},"rakes":{"M":[],"S":["Rake","Glance over","Blood","Rakehell","Rip"],"A":[]},"raking":{"M":[],"S":["Rake","Glance over","Skim","Crease","Run down"],"A":[]},"rakish":{"M":[],"S":["Snappy","Devil-may-care","Dapper","Raffish","Natty"],"A":[]},"rakishly":{"M":[["Adverb","in a rakish manner",[],["she wore her hat rakishly at an angle"]]],"S":["Raffishly","Carelessly","Rakishly"],"A":[]},"rakishness":{"M":[["Noun","the quality of a rake",["Dissoluteness","Incontinence","Self-gratification"],[]]],"S":["Rakishness","Jauntiness","Dapperness","Nattiness"],"A":[]},"rakishnesses":{"M":[],"S":["Rakishness","Jauntiness","Dapperness","Nattiness"],"A":[]},"rale":{"M":[],"S":["Rale","Rattle","Rattling"],"A":[]},"ralegh":{"M":[],"S":["Sir walter raleigh","Sir walter ralegh","Walter ralegh","Ralegh","Walter raleigh"],"A":[]},"raleigh":{"M":[["Noun","English courtier (a favorite of Elizabeth I) who tried to colonize Virginia; introduced potatoes and tobacco to England (1552-1618)",[],[]],["Noun","capital of the state of North Carolina; located in the east central part of the North Carolina",[],[]]],"S":["Capital of north carolina","Sir walter raleigh","Sir walter ralegh","Walter ralegh","Ralegh"],"A":[]},"rales":{"M":[],"S":["Rale","Rattle","Rattling"],"A":[]},"rallentando":{"M":[["Adverb","slowing down",[],["this passage should be played rallentando"]]],"S":["Rallentando","Ritardando","Ritenuto","Rit."],"A":[]},"rallidae":{"M":[["Noun","rails; crakes; gallinules; coots",["Bird family"],[]]],"S":["Rallidae","Family rallidae"],"A":[]},"rallied":{"M":[],"S":["Come up","Twit","Muster up","Mobilize","Ride"],"A":["demobilize"]},"rallies":{"M":[],"S":["Come up","Twit","Muster up","Mobilize","Mass meeting"],"A":["demobilize"]},"rally":{"M":[["Noun","a large gathering of people intended to arouse enthusiasm",["Gathering","Assemblage"],[]],["Noun","the feat of mustering strength for a renewed effort",["Feat","Effort","Exploit"],["he singled to start a rally in the 9th inning","he feared the rallying of their troops for a counterattack"]],["Noun","a marked recovery of strength or spirits during an illness",["Convalescence","Recuperation","Recovery"],[]],["Verb","return to a former condition",["Recover","Go back","Recuperate"],["The jilted lover soon rallied and found new friends","The stock market rallied"]],["Noun","(sports) an unbroken sequence of several successive strokes",["Group action"],["after a short rally Connors won the point"]]],"S":["Come up","Twit","Muster up","Mobilize","Mass meeting"],"A":["demobilize"]},"rallyes":{"M":[],"S":["Come up","Twit","Muster up","Mobilize","Ride"],"A":["demobilize"]},"rallying":{"M":[["Adjective","rousing or recalling to unity and renewed effort",[],["a rallying cry"]]],"S":["Come up","Twit","Muster up","Mobilize","Ride"],"A":["demobilize"]},"rallyings":{"M":[],"S":["Come up","Twit","Muster up","Mobilize","Ride"],"A":["demobilize"]},"ram":{"M":[["Noun","a tool for driving or forcing something by impact",["Tool"],[]],["Noun","uncastrated adult male sheep",["Sheep"],["a British term is `tup'"]],["Verb","strike or drive against with a heavy impact",["Thrust"],["ram the gate with a sledgehammer","pound on the door"]]],"S":["Pound","Random access memory","Random-access memory","Crash","Ram down"],"A":[]},"rama":{"M":[["Noun","avatar of Vishnu whose name is synonymous with God; any of three incarnations: Ramachandra or Parashurama or Balarama",[],["in Hindu folklore Rama is the epitome of chivalry and courage and obedience to sacred law"]]],"S":["Rama"],"A":[]},"ramachandra":{"M":[["Noun","a hero in Hindu mythology; an incarnation of Vishnu",[],[]]],"S":["Ramachandra"],"A":[]},"ramadan":{"M":[["Noun","the ninth month of the Islamic calendar; the month of fasting; the holiest period for the Islamic faith",["Islamic calendar month"],[]],["Noun","(Islam) a fast (held from sunrise to sunset) that is carried out during the Islamic month of Ramadan",["Fast","Fasting"],[]]],"S":["Ramadan"],"A":[]},"ramass":{"M":[],"S":["Rama"],"A":[]},"ramate":{"M":[],"S":["Ramous","Branching","Branched","Ramose","Ramate"],"A":[]},"ramayana":{"M":[["Noun","one of two classical Hindu epics telling of the banishment of Rama from his kingdom and the abduction of his wife by a demon and Rama's restoration to the throne",[],[]]],"S":["Ramayana"],"A":[]},"ramble":{"M":[["Noun","an aimless amble on a winding course",["Amble","Promenade","Saunter","Stroll","Perambulation"],[]]],"S":["Jog","Range","Vagabond","Tramp","Meander"],"A":[]},"rambled":{"M":[],"S":["Jog","Range","Vagabond","Tramp","Ramble on"],"A":[]},"rambler":{"M":[["Noun","a person who takes long walks in the country",["Pedestrian","Walker","Footer"],[]],["Noun","a person whose speech or writing is not well organized",["Communicator"],[]]],"S":["Rambler"],"A":[]},"ramblers":{"M":[],"S":["Rambler"],"A":[]},"rambles":{"M":[],"S":["Jog","Range","Vagabond","Tramp","Meander"],"A":[]},"rambling":{"M":[],"S":["Meandering","Wander","Excursive","Digressive","Sprawling"],"A":[]},"ramblingly":{"M":[],"S":["Ramblingly","Discursively"],"A":[]},"ramblings":{"M":[],"S":["Jog","Range","Vagabond","Tramp","Ramble on"],"A":[]},"rambouillet":{"M":[["Noun","hardy sheep developed from the merino producing both good mutton and fine wool",["Domestic sheep","Ovis aries"],[]]],"S":["Rambouillet"],"A":[]},"rambunctious":{"M":[],"S":["Robustious","Rumbustious","Unruly","Rambunctious","Boisterous"],"A":[]},"rambutan":{"M":[["Noun","Malayan tree bearing spiny red fruit",["Fruit tree"],[]],["Noun","pleasantly acid bright red oval Malayan fruit covered with soft spines",["Edible fruit"],[]]],"S":["Rambutan tree","Rambutan","Nephelium lappaceum","Rambotan"],"A":[]},"rambutans":{"M":[],"S":["Rambutan tree","Rambutan","Nephelium lappaceum","Rambotan"],"A":[]},"rameau":{"M":[["Noun","French composer of operas whose writings laid the foundation for the modern theory of harmony (1683-1764)",[],[]]],"S":["Jean-philippe rameau","Rameau"],"A":[]},"ramed":{"M":[],"S":["Pound","Crash","Ram down","Jam","Chock up"],"A":[]},"ramee":{"M":[],"S":["Chinese silk plant","Ramie","Ramee","China grass","Boehmeria nivea"],"A":[]},"ramees":{"M":[],"S":["Chinese silk plant","Ramie","Ramee","China grass","Boehmeria nivea"],"A":[]},"ramekin":{"M":[["Noun","a cheese dish made with egg and bread crumbs that is baked and served in individual fireproof dishes",["Dish"],[]],["Noun","a small fireproof dish used for baking and serving individual portions",["Dish"],[]]],"S":["Ramequin","Ramekin"],"A":[]},"ramekins":{"M":[],"S":["Ramequin","Ramekin"],"A":[]},"ramequin":{"M":[],"S":["Ramequin","Ramekin"],"A":[]},"ramequins":{"M":[],"S":["Ramequin","Ramekin"],"A":[]},"rameses":{"M":[["Noun","any of 12 kings of ancient Egypt between 1315 and 1090 BC",[],[]]],"S":["Pound","Rameses","Crash","Ram down","Ramses"],"A":[]},"ramesses":{"M":[],"S":["Pound","Rameses","Crash","Ram down","Ramses"],"A":[]},"rami":{"M":[],"S":["Ramus"],"A":[]},"ramie":{"M":[["Noun","tall perennial herb of tropical Asia with dark green leaves; cultivated for the fiber from its woody stems that resembles flax",["False nettle","Bog hemp"],[]]],"S":["Chinese silk plant","Ramie","Ramee","China grass","Boehmeria nivea"],"A":[]},"ramies":{"M":[],"S":["Chinese silk plant","Ramie","Ramee","China grass","Boehmeria nivea"],"A":[]},"ramification":{"M":[["Noun","an arrangement of branching parts",["Placement","Arrangement"],[]]],"S":["Complication","Forking","Branch","Branching","Fork"],"A":[]},"ramifications":{"M":[],"S":["Complication","Forking","Branch","Branching","Fork"],"A":[]},"ramified":{"M":[],"S":["Ramify","Separate","Branch","Fork","Furcate"],"A":[]},"ramifies":{"M":[],"S":["Ramify","Separate","Branch","Fork","Furcate"],"A":[]},"ramify":{"M":[["Verb","grow and send out branches or branch-like structures",["Grow"],["these plants ramify early and get to be very large"]]],"S":["Ramify","Separate","Branch","Fork","Furcate"],"A":[]},"ramifying":{"M":[],"S":["Ramify","Separate","Branch","Fork","Furcate"],"A":[]},"ramjet":{"M":[["Noun","a simple type of jet engine; must be launched at high speed",["Jet engine"],[]]],"S":["Ramjet engine","Ramjet","Flying drainpipe","Atherodyde","Athodyd"],"A":[]},"ramjets":{"M":[],"S":["Ramjet engine","Ramjet","Flying drainpipe","Atherodyde","Athodyd"],"A":[]},"ramman":{"M":[["Noun","god of storms and wind; corresponds to Babylonian Adad",[],[]]],"S":["Ramman"],"A":[]},"rammed":{"M":[],"S":["Pound","Crash","Ram down","Jam","Chock up"],"A":[]},"rammer":{"M":[["Noun","a tool for driving something with force",["Ram"],[]]],"S":["Rammer"],"A":[]},"rammers":{"M":[],"S":["Rammer"],"A":[]},"ramming":{"M":[],"S":["Pound","Crash","Ram down","Jam","Chock up"],"A":[]},"ramona":{"M":[],"S":["Salvia officinalis","Ramona","Common sage"],"A":[]},"ramose":{"M":[],"S":["Ramous","Branching","Branched","Ramose","Ramate"],"A":[]},"ramous":{"M":[],"S":["Ramous","Branching","Branched","Ramose","Ramate"],"A":[]},"ramp":{"M":[["Verb","behave violently, as if in state of a great anger",["Act","Behave","Do"],[]],["Verb","furnish with a ramp",["Supply","Provide","Render","Furnish"],["The ramped auditorium"]],["Verb","be rampant",["Model","Pose","Sit","Posture"],["the lion is rampant in this heraldic depiction"]],["Verb","creep up -- used especially of plants",["Climb","Climb up","Mount","Go up"],["The roses ramped over the wall"]],["Verb","stand with arms or forelegs raised, as if menacing",["Stand","Stand up"],[]]],"S":["Allium tricoccum","Ramp","Wild leek","Storm","Rage"],"A":[]},"rampage":{"M":[["Verb","act violently, recklessly, or destructively",["Act","Move"],[]]],"S":["Rampage","Violent disorder"],"A":[]},"rampaged":{"M":[],"S":["Rampage"],"A":[]},"rampageous":{"M":[["Adjective","displaying raging violence; often destructive",[],["the hot rampageous horses of my will\"- W.H.Auden"]]],"S":["Rampageous"],"A":[]},"rampages":{"M":[],"S":["Rampage","Violent disorder"],"A":[]}}